<?xml version="1.0" ?>
<!DOCTYPE PubmedArticleSet PUBLIC "-//NLM//DTD PubMedArticle, 1st January 2024//EN" "https://dtd.nlm.nih.gov/ncbi/pubmed/out/pubmed_240101.dtd">
<PubmedArticleSet>
<PubmedArticle><MedlineCitation Status="PubMed-not-MEDLINE" Owner="NLM"><PMID Version="1">36769807</PMID><DateRevised><Year>2023</Year><Month>02</Month><Day>14</Day></DateRevised><Article PubModel="Electronic"><Journal><ISSN IssnType="Print">2077-0383</ISSN><JournalIssue CitedMedium="Print"><Volume>12</Volume><Issue>3</Issue><PubDate><Year>2023</Year><Month>Feb</Month><Day>01</Day></PubDate></JournalIssue><Title>Journal of clinical medicine</Title><ISOAbbreviation>J Clin Med</ISOAbbreviation></Journal><ArticleTitle>Risk of New-Onset Diabetes Mellitus as a Post-COVID-19 Condition and Possible Mechanisms: A Scoping Review.</ArticleTitle><ELocationID EIdType="pii" ValidYN="Y">1159</ELocationID><ELocationID EIdType="doi" ValidYN="Y">10.3390/jcm12031159</ELocationID><Abstract><AbstractText>Long-term effects of COVID-19 are becoming more apparent even as the severity of acute infection is decreasing due to vaccinations and treatment. In this scoping review, we explored the current literature for the relationship between COVID-19 infection and new-onset diabetes mellitus four weeks after acute infection. We systematically searched the peer-reviewed literature published in English between 1 January 2020 and 31 August 2022 to study the risk of new-onset diabetes mellitus post-COVID-19 infection. This scoping review yielded 11 articles based on our inclusion and exclusion criteria. Except for one, all studies suggested an increased risk of new-onset diabetes mellitus 4 weeks after acute infection. This risk appears most in the first six months after the acute COVID-19 infection and seems to increase in a graded fashion based on the severity of the initial COVID-19 infection. Our review suggests a possible association of new-onset diabetes mellitus 4 weeks after acute COVID-19 infection. Since the severity of COVID-19 infection is associated with the development of post-infectious diabetes, vaccination that reduces the severity of acute COVID-19 infection might help to reduce the risk of post-COVID-19 diabetes mellitus. More studies are needed to better understand and quantify the association of post-COVID-19 conditions with diabetes and the role of vaccination in influencing it.</AbstractText></Abstract><AuthorList CompleteYN="Y"><Author ValidYN="Y"><LastName>Chourasia</LastName><ForeName>Prabal</ForeName><Initials>P</Initials><Identifier Source="ORCID">0000-0001-8685-0599</Identifier><AffiliationInfo><Affiliation>Department of Hospital Medicine, Mary Washington Hospital, Fredericksburg, VA 22401, USA.</Affiliation></AffiliationInfo></Author><Author ValidYN="Y"><LastName>Goyal</LastName><ForeName>Lokesh</ForeName><Initials>L</Initials><AffiliationInfo><Affiliation>Department of Hospital Medicine, Christus Spohn Hospital Corpus Christ, Shoreline, TX 78404, USA.</Affiliation></AffiliationInfo></Author><Author ValidYN="Y"><LastName>Kansal</LastName><ForeName>Dhruv</ForeName><Initials>D</Initials><AffiliationInfo><Affiliation>Yale Waterbury Internal Medicine Program, Waterbury Hospital, Waterbury, CT 06708, USA.</Affiliation></AffiliationInfo></Author><Author ValidYN="Y"><LastName>Roy</LastName><ForeName>Sasmit</ForeName><Initials>S</Initials><AffiliationInfo><Affiliation>Department of Nephrology, Centra Lynchburg General Hospital, Lynchburg, VA 24501, USA.</Affiliation></AffiliationInfo></Author><Author ValidYN="Y"><LastName>Singh</LastName><ForeName>Rohit</ForeName><Initials>R</Initials><Identifier Source="ORCID">0000-0003-2740-9386</Identifier><AffiliationInfo><Affiliation>Department of Hemato-Oncology, University of Vermont Medical Center, Burlington, VT 05401, USA.</Affiliation></AffiliationInfo></Author><Author ValidYN="Y"><LastName>Mahata</LastName><ForeName>Indrajeet</ForeName><Initials>I</Initials><AffiliationInfo><Affiliation>Department of Cardiology, University of Missouri, Springfield, MO 65804, USA.</Affiliation></AffiliationInfo></Author><Author ValidYN="Y"><LastName>Sheikh</LastName><ForeName>Abu Baker</ForeName><Initials>AB</Initials><Identifier Source="ORCID">0000-0003-0503-6961</Identifier><AffiliationInfo><Affiliation>Department of Internal Medicine, University of New Mexico Health Sciences Center, Albuquerque, NM 87106, USA.</Affiliation></AffiliationInfo></Author><Author ValidYN="Y"><LastName>Shekhar</LastName><ForeName>Rahul</ForeName><Initials>R</Initials><Identifier Source="ORCID">0000-0002-1200-6886</Identifier><AffiliationInfo><Affiliation>Department of Internal Medicine, University of New Mexico Health Sciences Center, Albuquerque, NM 87106, USA.</Affiliation></AffiliationInfo></Author></AuthorList><Language>eng</Language><PublicationTypeList><PublicationType UI="D016428">Journal Article</PublicationType><PublicationType UI="D016454">Review</PublicationType></PublicationTypeList><ArticleDate DateType="Electronic"><Year>2023</Year><Month>02</Month><Day>01</Day></ArticleDate></Article><MedlineJournalInfo><Country>Switzerland</Country><MedlineTA>J Clin Med</MedlineTA><NlmUniqueID>101606588</NlmUniqueID><ISSNLinking>2077-0383</ISSNLinking></MedlineJournalInfo><KeywordList Owner="NOTNLM"><Keyword MajorTopicYN="N">COVID-19 infection</Keyword><Keyword MajorTopicYN="N">long COVID-19</Keyword><Keyword MajorTopicYN="N">new-onset diabetes mellitus</Keyword><Keyword MajorTopicYN="N">post-COVID condition</Keyword></KeywordList><CoiStatement>The authors declare no conflict of interest.</CoiStatement></MedlineCitation><PubmedData><History><PubMedPubDate PubStatus="received"><Year>2022</Year><Month>12</Month><Day>13</Day></PubMedPubDate><PubMedPubDate PubStatus="revised"><Year>2023</Year><Month>1</Month><Day>11</Day></PubMedPubDate><PubMedPubDate PubStatus="accepted"><Year>2023</Year><Month>1</Month><Day>30</Day></PubMedPubDate><PubMedPubDate PubStatus="entrez"><Year>2023</Year><Month>2</Month><Day>11</Day><Hour>1</Hour><Minute>28</Minute></PubMedPubDate><PubMedPubDate PubStatus="pubmed"><Year>2023</Year><Month>2</Month><Day>12</Day><Hour>6</Hour><Minute>0</Minute></PubMedPubDate><PubMedPubDate PubStatus="medline"><Year>2023</Year><Month>2</Month><Day>12</Day><Hour>6</Hour><Minute>1</Minute></PubMedPubDate><PubMedPubDate PubStatus="pmc-release"><Year>2023</Year><Month>2</Month><Day>1</Day></PubMedPubDate></History><PublicationStatus>epublish</PublicationStatus><ArticleIdList><ArticleId IdType="pubmed">36769807</ArticleId><ArticleId IdType="pmc">PMC9917823</ArticleId><ArticleId IdType="doi">10.3390/jcm12031159</ArticleId><ArticleId IdType="pii">jcm12031159</ArticleId></ArticleIdList><ReferenceList><Reference><Citation>WHO Coronavirus (COVID-19) Dashboard. WHO Coronavirus (COVID-19) Dashboard with Vaccination Data.  [(accessed on 8 October 2022)].  Available online:  https://covid19.who.int/</Citation></Reference><Reference><Citation>Goyal L., Zapata M., Ajmera K., Chaurasia P., Pandit R., Pandit T. A Hitchhiker&#x2019;s Guide to Worldwide COVID-19 Vaccinations: A Detailed Review of Monovalent and Bivalent Vaccine Schedules, COVID-19 Vaccine Side Effects, and Effectiveness Against Omicron and Delta Variants. Cureus. 2022;14:e29837. doi: 10.7759/cureus.29837.</Citation><ArticleIdList><ArticleId IdType="doi">10.7759/cureus.29837</ArticleId><ArticleId IdType="pmc">PMC9527088</ArticleId><ArticleId IdType="pubmed">36204257</ArticleId></ArticleIdList></Reference><Reference><Citation>Centers for Disease Control and Prevention (CDC)  Long COVID or Post-COVID Conditions.  [(accessed on 4 October 2022)]; Available online:  https://www.cdc.gov/coronavirus/2019-ncov/long-term-effects/index.html.</Citation></Reference><Reference><Citation>Su Y., Yuan D., Chen D.G., Ng R.H., Wang K., Choi J., Li S., Hong S., Zhang R., Xie J., et al. Multiple early factors anticipate post-acute COVID-19 sequelae. Cell. 2022;185:881&#x2013;895.e20. doi: 10.1016/j.cell.2022.01.014.</Citation><ArticleIdList><ArticleId IdType="doi">10.1016/j.cell.2022.01.014</ArticleId><ArticleId IdType="pmc">PMC8786632</ArticleId><ArticleId IdType="pubmed">35216672</ArticleId></ArticleIdList></Reference><Reference><Citation>Sudre C.H., Murray B., Varsavsky T., Graham M.S., Penfold R.S., Bowyer R.C., Pujol J.C., Klaser K., Antonelli M., Canas L.S., et al. Attributes and predictors of long COVID. Nat. Med. 2021;27:626&#x2013;631. doi: 10.1038/s41591-021-01292-y.</Citation><ArticleIdList><ArticleId IdType="doi">10.1038/s41591-021-01292-y</ArticleId><ArticleId IdType="pmc">PMC7611399</ArticleId><ArticleId IdType="pubmed">33692530</ArticleId></ArticleIdList></Reference><Reference><Citation>Corrao S., Pinelli K., Vacca M., Raspanti M., Argano C. Type 2 Diabetes Mellitus and COVID-19: A Narrative Review. Front. Endocrinol. 2021;12:609470. doi: 10.3389/fendo.2021.609470.</Citation><ArticleIdList><ArticleId IdType="doi">10.3389/fendo.2021.609470</ArticleId><ArticleId IdType="pmc">PMC8044543</ArticleId><ArticleId IdType="pubmed">33868163</ArticleId></ArticleIdList></Reference><Reference><Citation>Metwally A.A., Mehta P., Johnson B.S., Nagarjuna A., Snyder M.P. COVID-19-Induced New-Onset Diabetes: Trends and Technologies. Diabetes. 2021;70:2733&#x2013;2744. doi: 10.2337/dbi21-0029.</Citation><ArticleIdList><ArticleId IdType="doi">10.2337/dbi21-0029</ArticleId><ArticleId IdType="pmc">PMC8660988</ArticleId><ArticleId IdType="pubmed">34686519</ArticleId></ArticleIdList></Reference><Reference><Citation>Khunti K., Del Prato S., Mathieu C., Kahn S.E., Gabbay R.A., Buse J.B. COVID-19, Hyperglycemia, and New-Onset Diabetes. Diabetes Care. 2021;44:2645&#x2013;2655. doi: 10.2337/dc21-1318.</Citation><ArticleIdList><ArticleId IdType="doi">10.2337/dc21-1318</ArticleId><ArticleId IdType="pmc">PMC8669536</ArticleId><ArticleId IdType="pubmed">34625431</ArticleId></ArticleIdList></Reference><Reference><Citation>American Diabetes Association (ADA)  Diagnosis.  [(accessed on 12 October 2022)].  Available online:  https://diabetes.org/diabetes/a1c/diagnosis.</Citation></Reference><Reference><Citation>Xie Y., Al-Aly Z. Risks and burdens of incident diabetes in long COVID: A cohort study. Lancet Diabetes Endocrinol. 2022;10:311&#x2013;321. doi: 10.1016/S2213-8587(22)00044-4.</Citation><ArticleIdList><ArticleId IdType="doi">10.1016/S2213-8587(22)00044-4</ArticleId><ArticleId IdType="pmc">PMC8937253</ArticleId><ArticleId IdType="pubmed">35325624</ArticleId></ArticleIdList></Reference><Reference><Citation>Estiri H., Strasser Z.H., Brat G.A., Semenov Y.R., Consortium for Characterization of COVID-19 by EHR (4CE) Patel C.J., Murphy S.N. Evolving phenotypes of non-hospitalized patients that indicate long COVID. BMC Med. 2021;19:249. doi: 10.1186/s12916-021-02115-0.</Citation><ArticleIdList><ArticleId IdType="doi">10.1186/s12916-021-02115-0</ArticleId><ArticleId IdType="pmc">PMC8474909</ArticleId><ArticleId IdType="pubmed">34565368</ArticleId></ArticleIdList></Reference><Reference><Citation>Daugherty S.E., Guo Y., Heath K., Dasmari&#xf1;as M.C., Jubilo K.G., Samranvedhya J., Lipsitch M., Cohen K. Risk of clinical sequelae after the acute phase of SARS-CoV-2 infection: Retrospective cohort study. BMJ. 2021;373:n1098. doi: 10.1136/bmj.n1098.</Citation><ArticleIdList><ArticleId IdType="doi">10.1136/bmj.n1098</ArticleId><ArticleId IdType="pmc">PMC8132065</ArticleId><ArticleId IdType="pubmed">34011492</ArticleId></ArticleIdList></Reference><Reference><Citation>Birabaharan M., Kaelber D.C., Pettus J.H., Smith D.M. Risk of new-onset type 2 diabetes in 600&#x2009;055 people after COVID-19: A cohort study. Diabetes Obes. Metab. 2022;24:1176&#x2013;1179. doi: 10.1111/dom.14659.</Citation><ArticleIdList><ArticleId IdType="doi">10.1111/dom.14659</ArticleId><ArticleId IdType="pmc">PMC9035030</ArticleId><ArticleId IdType="pubmed">35112782</ArticleId></ArticleIdList></Reference><Reference><Citation>Rathmann W., Kuss O., Kostev K. Incidence of newly diagnosed diabetes after Covid-19. Diabetologia. 2022;65:949&#x2013;954. doi: 10.1007/s00125-022-05670-0.</Citation><ArticleIdList><ArticleId IdType="doi">10.1007/s00125-022-05670-0</ArticleId><ArticleId IdType="pmc">PMC8923743</ArticleId><ArticleId IdType="pubmed">35292829</ArticleId></ArticleIdList></Reference><Reference><Citation>Rezel-Potts E., Douiri A., Sun X., Chowienczyk P.J., Shah A.M., Gulliford M.C. Cardiometabolic outcomes up to 12 months after COVID-19 infection. A matched cohort study in the UK. PLoS Med. 2022;19:e1004052. doi: 10.1371/journal.pmed.1004052.</Citation><ArticleIdList><ArticleId IdType="doi">10.1371/journal.pmed.1004052</ArticleId><ArticleId IdType="pmc">PMC9295991</ArticleId><ArticleId IdType="pubmed">35853019</ArticleId></ArticleIdList></Reference><Reference><Citation>Montefusco L., Ben Nasr M., D&#x2019;Addio F., Loretelli C., Rossi A., Pastore I., Daniele G., Abdelsalam A., Maestroni A., Dell&#x2019;Acqua M., et al. Acute and long-term disruption of glycometabolic control after SARS-CoV-2 infection. Nat. Metab. 2021;3:774&#x2013;785. doi: 10.1038/s42255-021-00407-6.</Citation><ArticleIdList><ArticleId IdType="doi">10.1038/s42255-021-00407-6</ArticleId><ArticleId IdType="pmc">PMC9931026</ArticleId><ArticleId IdType="pubmed">34035524</ArticleId></ArticleIdList></Reference><Reference><Citation>Laurenzi A., Caretto A., Molinari C., Mercalli A., Melzi R., Nano R., Tresoldi C., Rovere Querini P., Ciceri F., Lampasona V., et al. No Evidence of Long-Term Disruption of Glycometabolic Control After SARS-CoV-2 Infection. J. Clin. Endocrinol. Metab. 2022;107:e1009&#x2013;e1019. doi: 10.1210/clinem/dgab792.</Citation><ArticleIdList><ArticleId IdType="doi">10.1210/clinem/dgab792</ArticleId><ArticleId IdType="pmc">PMC8691144</ArticleId><ArticleId IdType="pubmed">34718627</ArticleId></ArticleIdList></Reference><Reference><Citation>Maestre-Mu&#xf1;iz M.M., Arias &#xc1;., Mata-V&#xe1;zquez E., Mart&#xed;n-Toledano M., L&#xf3;pez-Larramona G., Ruiz-Chicote A.M., Nieto-Sandoval B., Lucendo A.J. Long-Term Outcomes of Patients with Coronavirus Disease 2019 at One Year after Hospital Discharge. J. Clin. Med. 2021;10:2945. doi: 10.3390/jcm10132945.</Citation><ArticleIdList><ArticleId IdType="doi">10.3390/jcm10132945</ArticleId><ArticleId IdType="pmc">PMC8269002</ArticleId><ArticleId IdType="pubmed">34209085</ArticleId></ArticleIdList></Reference><Reference><Citation>Zhang J., Shu T., Zhu R., Yang F., Zhang B., Lai X. The Long-Term Effect of COVID-19 Disease Severity on Risk of Diabetes Incidence and the Near 1-Year Follow-Up Outcomes among Postdischarge Patients in Wuhan. J. Clin. Med. 2022;11:3094. doi: 10.3390/jcm11113094.</Citation><ArticleIdList><ArticleId IdType="doi">10.3390/jcm11113094</ArticleId><ArticleId IdType="pmc">PMC9181214</ArticleId><ArticleId IdType="pubmed">35683480</ArticleId></ArticleIdList></Reference><Reference><Citation>Ayoubkhani D., Khunti K., Nafilyan V., Maddox T., Humberstone B., Diamond I., Banerjee A. Post-covid syndrome in individuals admitted to hospital with covid-19: Retrospective cohort study. BMJ. 2021;372:n693. doi: 10.1136/bmj.n693.</Citation><ArticleIdList><ArticleId IdType="doi">10.1136/bmj.n693</ArticleId><ArticleId IdType="pmc">PMC8010267</ArticleId><ArticleId IdType="pubmed">33789877</ArticleId></ArticleIdList></Reference><Reference><Citation>Centers for Disease Control and Prevention (CDC)  Variants of the Virus.  [(accessed on 14 October 2022)]; Available online:  https://www.cdc.gov/coronavirus/2019-ncov/variants/index.html.</Citation></Reference><Reference><Citation>Thompson E.J., Williams D.M., Walker A.J., Mitchell R.E., Niedzwiedz C.L., Yang T.C., Huggins C.F., Kwong A.S.F., Silverwood R.J., Di Gessa G., et al. Long COVID burden and risk factors in 10 UK longitudinal studies and electronic health records. Nat. Commun. 2022;13:3528. doi: 10.1038/s41467-022-30836-0.</Citation><ArticleIdList><ArticleId IdType="doi">10.1038/s41467-022-30836-0</ArticleId><ArticleId IdType="pmc">PMC9240035</ArticleId><ArticleId IdType="pubmed">35764621</ArticleId></ArticleIdList></Reference><Reference><Citation>Fern&#xe1;ndez-de-Las-Pe&#xf1;as C., Guijarro C., Torres-Macho J., Velasco-Arribas M., Plaza-Canteli S., Hern&#xe1;ndez-Barrera V., Arias-Naval&#xf3;n J.A. Diabetes and the Risk of Long-term Post-COVID Symptoms. Diabetes. 2021;70:2917&#x2013;2921. doi: 10.2337/db21-0329.</Citation><ArticleIdList><ArticleId IdType="doi">10.2337/db21-0329</ArticleId><ArticleId IdType="pubmed">34580087</ArticleId></ArticleIdList></Reference><Reference><Citation>Zhang J., Kong W., Xia P., Xu Y., Li L., Li Q., Yang L., Wei Q., Wang H., Li H., et al. Impaired fasting glucose and diabetes are related to higher risks of complications and mortality among patients with coronavirus disease 2019. Front. Endocrinol. 2020;11:525. doi: 10.3389/fendo.2020.00525.</Citation><ArticleIdList><ArticleId IdType="doi">10.3389/fendo.2020.00525</ArticleId><ArticleId IdType="pmc">PMC7365851</ArticleId><ArticleId IdType="pubmed">32754119</ArticleId></ArticleIdList></Reference><Reference><Citation>Liu Y., Lu R., Wang J., Cheng Q., Zhang R., Zhang S., Le Y., Wang H., Xiao W., Gao H., et al. Diabetes, even newly defined by HbA1c testing, is associated with an increased risk of in-hospital death in adults with COVID-19. BMC Endocr. Disord. 2021;21:56. doi: 10.1186/s12902-021-00717-6.</Citation><ArticleIdList><ArticleId IdType="doi">10.1186/s12902-021-00717-6</ArticleId><ArticleId IdType="pmc">PMC7995677</ArticleId><ArticleId IdType="pubmed">33771154</ArticleId></ArticleIdList></Reference><Reference><Citation>Yang J.-K., Zhao M.-M., Jin J.-M., Liu S., Bai P., He W., Wu F., Liu X.-F., Chai Z.-L., Han D.-M. New-onset COVID-19-related diabetes: An early indicator of multi-organ injury and mortally of SARS-CoV-2 infection. Curr. Med. 2022;1:6. doi: 10.1007/s44194-022-00006-x.</Citation><ArticleIdList><ArticleId IdType="doi">10.1007/s44194-022-00006-x</ArticleId><ArticleId IdType="pmc">PMC9132601</ArticleId><ArticleId IdType="pubmed">35673632</ArticleId></ArticleIdList></Reference><Reference><Citation>Chandrashekhar Joshi S., Pozzilli P. COVID-19 induced Diabetes: A novel presentation. Diabetes Res. Clin. Pract. 2022;191:110034. doi: 10.1016/j.diabres.2022.110034.</Citation><ArticleIdList><ArticleId IdType="doi">10.1016/j.diabres.2022.110034</ArticleId><ArticleId IdType="pmc">PMC9355745</ArticleId><ArticleId IdType="pubmed">35940303</ArticleId></ArticleIdList></Reference><Reference><Citation>Sathish T., Kapoor N., Cao Y., Tapp R.J., Zimmet P. Proportion of newly diagnosed diabetes in COVID-19 patients: A systematic review and meta-analysis. Diabetes Obes. Metab. 2021;23:870&#x2013;874. doi: 10.1111/dom.14269.</Citation><ArticleIdList><ArticleId IdType="doi">10.1111/dom.14269</ArticleId><ArticleId IdType="pmc">PMC7753574</ArticleId><ArticleId IdType="pubmed">33245182</ArticleId></ArticleIdList></Reference><Reference><Citation>Shrestha D.B., Budhathoki P., Raut S., Adhikari S., Ghimire P., Thapaliya S., Rabaan A.A., Karki B.J. New-onset diabetes in COVID-19 and clinical outcomes: A systematic review and meta-analysis. World J. Virol. 2021;10:275&#x2013;287. doi: 10.5501/wjv.v10.i5.275.</Citation><ArticleIdList><ArticleId IdType="doi">10.5501/wjv.v10.i5.275</ArticleId><ArticleId IdType="pmc">PMC8474977</ArticleId><ArticleId IdType="pubmed">34631477</ArticleId></ArticleIdList></Reference><Reference><Citation>U.S. Food and Drug Administration (FDA)  Takes Key Action in Fight Against COVID-19 By Issuing Emergency Use Authorization for First COVID-19 Vaccine.  [(accessed on 6 December 2022)]; Available online:  https://www.fda.gov/news-events/press-announcements/fda-takes-key-action-fight-against-covid-19-issuing-emergency-use-authorization-first-covid-19.</Citation></Reference><Reference><Citation>Moghadas S.M., Vilches T.N., Zhang K., Wells C.R., Shoukat A., Singer B.H., Meyers L.A., Neuzil K.M., Langley J.M., Fitzpatrick M.C., et al. The Impact of Vaccination on Coronavirus Disease 2019 (COVID-19) Outbreaks in the United States. Clin. Infect. Dis. 2021;73:2257&#x2013;2264. doi: 10.1093/cid/ciab079.</Citation><ArticleIdList><ArticleId IdType="doi">10.1093/cid/ciab079</ArticleId><ArticleId IdType="pmc">PMC7929033</ArticleId><ArticleId IdType="pubmed">33515252</ArticleId></ArticleIdList></Reference><Reference><Citation>Mohammed I., Nauman A., Paul P., Ganesan S., Chen K.-H., Jalil S.M.S., Jaouni S.H., Kawas H., Khan W.A., Vattoth A.L., et al. The efficacy and effectiveness of the COVID-19 vaccines in reducing infection, severity, hospitalization, and mortality: A systematic review. Hum. Vaccin. Immunother. 2022;18:2027160. doi: 10.1080/21645515.2022.2027160.</Citation><ArticleIdList><ArticleId IdType="doi">10.1080/21645515.2022.2027160</ArticleId><ArticleId IdType="pmc">PMC8862168</ArticleId><ArticleId IdType="pubmed">35113777</ArticleId></ArticleIdList></Reference><Reference><Citation>Hayden M.R. An Immediate and Long-Term Complication of COVID-19 May Be Type 2 Diabetes Mellitus: The Central Role of &#x3b2;-Cell Dysfunction, Apoptosis and Exploration of Possible Mechanisms. Cells. 2020;9:2475. doi: 10.3390/cells9112475.</Citation><ArticleIdList><ArticleId IdType="doi">10.3390/cells9112475</ArticleId><ArticleId IdType="pmc">PMC7697826</ArticleId><ArticleId IdType="pubmed">33202960</ArticleId></ArticleIdList></Reference><Reference><Citation>Rubino F., Amiel S.A., Zimmet P., Alberti G., Bornstein S., Eckel R.H., Mingrone G., Boehm B., Cooper M.E., Chai Z., et al. New-Onset Diabetes in Covid-19. N. Engl. J. Med. 2020;383:789&#x2013;790. doi: 10.1056/NEJMc2018688.</Citation><ArticleIdList><ArticleId IdType="doi">10.1056/NEJMc2018688</ArticleId><ArticleId IdType="pmc">PMC7304415</ArticleId><ArticleId IdType="pubmed">32530585</ArticleId></ArticleIdList></Reference><Reference><Citation>Babajide O.I., Ogbon E.O., Adelodun A., Agbalajobi O., Ogunsesan Y. COVID-19 and acute pancreatitis: A systematic review. JGH Open. 2022;6:231&#x2013;235. doi: 10.1002/jgh3.12729.</Citation><ArticleIdList><ArticleId IdType="doi">10.1002/jgh3.12729</ArticleId><ArticleId IdType="pmc">PMC9021704</ArticleId><ArticleId IdType="pubmed">35475200</ArticleId></ArticleIdList></Reference><Reference><Citation>Holshue M.L., DeBolt C., Lindquist S., Lofy K.H., Wiesman J., Bruce H., Spitters C., Ericson K., Wilkerson S., Tural A., et al. Washington State 2019-nCoV Case Investigation Team First case of 2019 novel coronavirus in the United States. N. Engl. J. Med. 2020;382:929&#x2013;936. doi: 10.1056/NEJMoa2001191.</Citation><ArticleIdList><ArticleId IdType="doi">10.1056/NEJMoa2001191</ArticleId><ArticleId IdType="pmc">PMC7092802</ArticleId><ArticleId IdType="pubmed">32004427</ArticleId></ArticleIdList></Reference><Reference><Citation>Mamtani M., Athavale A.M., Abraham M., Vernik J., Amarah A.R., Ruiz J.P., Joshi A.J., Itteera M., Zhukovski S.D., Madaiah R.P., et al. Association of hyperglycaemia with hospital mortality in nondiabetic COVID-19 patients: A cohort study. Diabetes Metab. 2021;47:101254. doi: 10.1016/j.diabet.2021.101254.</Citation><ArticleIdList><ArticleId IdType="doi">10.1016/j.diabet.2021.101254</ArticleId><ArticleId IdType="pmc">PMC7994287</ArticleId><ArticleId IdType="pubmed">33781926</ArticleId></ArticleIdList></Reference><Reference><Citation>Tamez-P&#xe9;rez H.E., Quintanilla-Flores D.L., Rodr&#xed;guez-Guti&#xe9;rrez R., Gonz&#xe1;lez-Gonz&#xe1;lez J.G., Tamez-Pe&#xf1;a A.L. Steroid hyperglycemia: Prevalence, early detection and therapeutic recommendations: A narrative review. World J. Diabetes. 2015;6:1073&#x2013;1081. doi: 10.4239/wjd.v6.i8.1073.</Citation><ArticleIdList><ArticleId IdType="doi">10.4239/wjd.v6.i8.1073</ArticleId><ArticleId IdType="pmc">PMC4515447</ArticleId><ArticleId IdType="pubmed">26240704</ArticleId></ArticleIdList></Reference><Reference><Citation>Ruzzin J., Wagman A.S., Jensen J. Glucocorticoid-induced insulin resistance in skeletal muscles: Defects in insulin signalling and the effects of a selective glycogen synthase kinase-3 inhibitor. Diabetologia. 2005;48:2119&#x2013;2130. doi: 10.1007/s00125-005-1886-0.</Citation><ArticleIdList><ArticleId IdType="doi">10.1007/s00125-005-1886-0</ArticleId><ArticleId IdType="pubmed">16078016</ArticleId></ArticleIdList></Reference><Reference><Citation>Clore J.N., Thurby-Hay L. Glucocorticoid-induced hyperglycemia. Endocr. Pract. 2009;15:469&#x2013;474. doi: 10.4158/EP08331.RAR.</Citation><ArticleIdList><ArticleId IdType="doi">10.4158/EP08331.RAR</ArticleId><ArticleId IdType="pubmed">19454391</ArticleId></ArticleIdList></Reference></ReferenceList></PubmedData></PubmedArticle></PubmedArticleSet>