<?xml version="1.0" ?>
<!DOCTYPE PubmedArticleSet PUBLIC "-//NLM//DTD PubMedArticle, 1st January 2024//EN" "https://dtd.nlm.nih.gov/ncbi/pubmed/out/pubmed_240101.dtd">
<PubmedArticleSet>
<PubmedArticle><MedlineCitation Status="PubMed-not-MEDLINE" Owner="NLM"><PMID Version="1">38623400</PMID><DateRevised><Year>2024</Year><Month>04</Month><Day>25</Day></DateRevised><Article PubModel="Electronic-eCollection"><Journal><ISSN IssnType="Electronic">2589-5370</ISSN><JournalIssue CitedMedium="Internet"><Volume>71</Volume><PubDate><Year>2024</Year><Month>May</Month></PubDate></JournalIssue><Title>EClinicalMedicine</Title><ISOAbbreviation>EClinicalMedicine</ISOAbbreviation></Journal><ArticleTitle>Lung outcomes and related risk factors in patients after SARS-CoV-2 infection: a hospitalised single-centre cohort from&#xa0;Johannesburg, South Africa.</ArticleTitle><Pagination><StartPage>102588</StartPage><MedlinePgn>102588</MedlinePgn></Pagination><ELocationID EIdType="pii" ValidYN="Y">102588</ELocationID><ELocationID EIdType="doi" ValidYN="Y">10.1016/j.eclinm.2024.102588</ELocationID><Abstract><AbstractText Label="BACKGROUND" NlmCategory="UNASSIGNED">Sequelae post-SARS-CoV-2 infection, including lung and functional impairment, pose a significant challenge post-recovery. We explored the burden and risk factors for post-COVID-19 sequelae in an African population with prevalent comorbidities including tuberculosis (TB) and HIV.</AbstractText><AbstractText Label="METHODS" NlmCategory="UNASSIGNED">We conducted an observational cohort study on hospitalised adults with confirmed SARS-CoV-2 infection from 20 March to 06 October 2021&#xa0;at Chris Hani Baragwanath Academic Hospital, South Africa. We collected data on comorbidities, and COVID-19 severity using the World Health Organization (WHO) clinical progression scale. Prospectively, we followed up all participants within 40-days post-discharge to assess body mass index (BMI), COVID-19 symptoms and quality of life using St George's Respiratory Questionnaire (SGRQ), 6-min walking-test (6MWT), and spirometry. A subsequent in-depth visit assessed plethysmography, diffusing capacity for the lung for carbon monoxide (DLCO), and high-resolution chest-CT.</AbstractText><AbstractText Label="FINDINGS" NlmCategory="UNASSIGNED">We followed up 111 participants, where 65.8% were female, median age 50.5 years, and predominantly black-African (92.8%). Relevant comorbidities included TB disease (18.9%) and HIV infection (36%). SGRQ total scores were elevated in 78.9%, median 6MWT distance was reduced at 300&#xa0;m (IQR 210-400), and nearly half (49.5%) exhibited spirometry findings below the lower limit of normal (LLN). In-depth pulmonary assessment for 61 participants revealed abnormalities in total lung capacity (31.6%&#xa0;&lt;80% predicted), DLCO (53.4%&#xa0;&lt;80% predicted), and chest-CT (86.7% abnormal). Significant risk factors for individual abnormal outcomes, adjusted for age and sex, were TB disease, HIV with CD4 &lt;200&#xa0;cells/mm<sup>3</sup>, BMI &lt;18.5&#xa0;kg/m<sup>2</sup> and &gt;35&#xa0;kg/m<sup>2</sup>, and initial COVID-19 severity.</AbstractText><AbstractText Label="INTERPRETATION" NlmCategory="UNASSIGNED">This study demonstrates substantial lung and functional morbidity within the first weeks post-COVID-19, particularly in individuals with pre-existing comorbidities including TB, HIV, and low or high BMI. Chest-CT and DLCO show best early potential at reflecting COVID-19-related pathologies.</AbstractText><AbstractText Label="FUNDING" NlmCategory="UNASSIGNED">The Bavarian State Ministry of Science and Arts.</AbstractText><CopyrightInformation>&#xa9; 2024 The Author(s).</CopyrightInformation></Abstract><AuthorList CompleteYN="Y"><Author ValidYN="Y"><LastName>Glover</LastName><ForeName>Nicole Audrey</ForeName><Initials>NA</Initials><AffiliationInfo><Affiliation>The Aurum Institute, Johannesburg, South Africa.</Affiliation></AffiliationInfo></Author><Author ValidYN="Y"><LastName>Ivanova</LastName><ForeName>Olena</ForeName><Initials>O</Initials><AffiliationInfo><Affiliation>Division of Infectious Diseases and Tropical Medicine, LMU University Hospital, LMU Munich.</Affiliation></AffiliationInfo></Author><Author ValidYN="Y"><LastName>Sathar</LastName><ForeName>Farzana</ForeName><Initials>F</Initials><AffiliationInfo><Affiliation>The Aurum Institute, Johannesburg, South Africa.</Affiliation></AffiliationInfo></Author><Author ValidYN="Y"><LastName>Riess</LastName><ForeName>Friedrich</ForeName><Initials>F</Initials><AffiliationInfo><Affiliation>Division of Infectious Diseases and Tropical Medicine, LMU University Hospital, LMU Munich.</Affiliation></AffiliationInfo></Author><Author ValidYN="Y"><LastName>Shambhu</LastName><ForeName>Rekha Rao</ForeName><Initials>RR</Initials><AffiliationInfo><Affiliation>Division of Infectious Diseases and Tropical Medicine, LMU University Hospital, LMU Munich.</Affiliation></AffiliationInfo></Author><Author ValidYN="Y"><LastName>Mekota</LastName><ForeName>Anna-Maria</ForeName><Initials>AM</Initials><AffiliationInfo><Affiliation>Division of Infectious Diseases and Tropical Medicine, LMU University Hospital, LMU Munich.</Affiliation></AffiliationInfo></Author><Author ValidYN="Y"><LastName>Zurba</LastName><ForeName>Lindsay</ForeName><Initials>L</Initials><AffiliationInfo><Affiliation>Education for Health Africa, Durban, South Africa.</Affiliation></AffiliationInfo></Author><Author ValidYN="Y"><LastName>Menezes</LastName><ForeName>Colin</ForeName><Initials>C</Initials><AffiliationInfo><Affiliation>University of the Witwatersrand, Department of Internal Medicine, Chris Hani Baragwanath Academic Hospital, Johannesburg, South Africa.</Affiliation></AffiliationInfo></Author><Author ValidYN="Y"><LastName>Alexandra van Blydenstein</LastName><ForeName>Sarah</ForeName><Initials>S</Initials><AffiliationInfo><Affiliation>University of the Witwatersrand, Department of Internal Medicine, Chris Hani Baragwanath Academic Hospital, Johannesburg, South Africa.</Affiliation></AffiliationInfo></Author><Author ValidYN="Y"><LastName>Kalla</LastName><ForeName>Ismail</ForeName><Initials>I</Initials><AffiliationInfo><Affiliation>University of the Witwatersrand, Department of Internal Medicine, Charlotte Maxeke Johannesburg Academic Hospital, Johannesburg, South Africa.</Affiliation></AffiliationInfo></Author><Author ValidYN="Y"><LastName>Hoelscher</LastName><ForeName>Michael</ForeName><Initials>M</Initials><AffiliationInfo><Affiliation>Division of Infectious Diseases and Tropical Medicine, LMU University Hospital, LMU Munich.</Affiliation></AffiliationInfo><AffiliationInfo><Affiliation>German Centre for Infection Research (DZIF), Partner Site Munich, Munich, Germany.</Affiliation></AffiliationInfo><AffiliationInfo><Affiliation>Unit Global Health, Helmholtz Zentrum M&#xfc;nchen, German Research Centre for Environmental Health (HMGU), Neuherberg, Germany.</Affiliation></AffiliationInfo></Author><Author ValidYN="Y"><LastName>Saathoff</LastName><ForeName>Elmar</ForeName><Initials>E</Initials><AffiliationInfo><Affiliation>Division of Infectious Diseases and Tropical Medicine, LMU University Hospital, LMU Munich.</Affiliation></AffiliationInfo><AffiliationInfo><Affiliation>German Centre for Infection Research (DZIF), Partner Site Munich, Munich, Germany.</Affiliation></AffiliationInfo></Author><Author ValidYN="Y"><LastName>Charalambous</LastName><ForeName>Salome</ForeName><Initials>S</Initials><AffiliationInfo><Affiliation>The Aurum Institute, Johannesburg, South Africa.</Affiliation></AffiliationInfo><AffiliationInfo><Affiliation>School of Public Health, University of the Witwatersrand, Johannesburg, South Africa.</Affiliation></AffiliationInfo></Author><Author ValidYN="Y"><LastName>Rachow</LastName><ForeName>Andrea</ForeName><Initials>A</Initials><AffiliationInfo><Affiliation>Division of Infectious Diseases and Tropical Medicine, LMU University Hospital, LMU Munich.</Affiliation></AffiliationInfo><AffiliationInfo><Affiliation>German Centre for Infection Research (DZIF), Partner Site Munich, Munich, Germany.</Affiliation></AffiliationInfo><AffiliationInfo><Affiliation>Unit Global Health, Helmholtz Zentrum M&#xfc;nchen, German Research Centre for Environmental Health (HMGU), Neuherberg, Germany.</Affiliation></AffiliationInfo></Author></AuthorList><Language>eng</Language><PublicationTypeList><PublicationType UI="D016428">Journal Article</PublicationType></PublicationTypeList><ArticleDate DateType="Electronic"><Year>2024</Year><Month>04</Month><Day>11</Day></ArticleDate></Article><MedlineJournalInfo><Country>England</Country><MedlineTA>EClinicalMedicine</MedlineTA><NlmUniqueID>101733727</NlmUniqueID><ISSNLinking>2589-5370</ISSNLinking></MedlineJournalInfo><KeywordList Owner="NOTNLM"><Keyword MajorTopicYN="N">Africa</Keyword><Keyword MajorTopicYN="N">COVID-19</Keyword><Keyword MajorTopicYN="N">HIV</Keyword><Keyword MajorTopicYN="N">Long-COVID</Keyword><Keyword MajorTopicYN="N">Post-COVID-19</Keyword><Keyword MajorTopicYN="N">Tuberculosis</Keyword></KeywordList><CoiStatement>Andrea Rachow declares a grant obtained from Bundesministerium f&#xfc;r Bildung und Forschung (BMBF) for post-TB research. All other authors declare no competing interests.</CoiStatement></MedlineCitation><PubmedData><History><PubMedPubDate PubStatus="received"><Year>2024</Year><Month>1</Month><Day>16</Day></PubMedPubDate><PubMedPubDate PubStatus="revised"><Year>2024</Year><Month>3</Month><Day>20</Day></PubMedPubDate><PubMedPubDate PubStatus="accepted"><Year>2024</Year><Month>3</Month><Day>21</Day></PubMedPubDate><PubMedPubDate PubStatus="medline"><Year>2024</Year><Month>4</Month><Day>16</Day><Hour>12</Hour><Minute>43</Minute></PubMedPubDate><PubMedPubDate PubStatus="pubmed"><Year>2024</Year><Month>4</Month><Day>16</Day><Hour>12</Hour><Minute>42</Minute></PubMedPubDate><PubMedPubDate PubStatus="entrez"><Year>2024</Year><Month>4</Month><Day>16</Day><Hour>3</Hour><Minute>39</Minute></PubMedPubDate><PubMedPubDate PubStatus="pmc-release"><Year>2024</Year><Month>4</Month><Day>11</Day></PubMedPubDate></History><PublicationStatus>epublish</PublicationStatus><ArticleIdList><ArticleId IdType="pubmed">38623400</ArticleId><ArticleId IdType="pmc">PMC11016864</ArticleId><ArticleId IdType="doi">10.1016/j.eclinm.2024.102588</ArticleId><ArticleId IdType="pii">S2589-5370(24)00167-6</ArticleId></ArticleIdList><ReferenceList><Reference><Citation>Groff D., Sun A., Ssentongo A.E., et al. Short-term and long-term rates of postacute sequelae of SARS-CoV-2 infection: a systematic review. JAMA Netw Open. 2021;4(10)</Citation><ArticleIdList><ArticleId IdType="pmc">PMC8515212</ArticleId><ArticleId IdType="pubmed">34643720</ArticleId></ArticleIdList></Reference><Reference><Citation>Steinbeis F., Thibeault C., Doellinger F., et al. Severity of respiratory failure and computed chest tomography in acute COVID-19 correlates with pulmonary function and respiratory symptoms after infection with SARS-CoV-2: an observational longitudinal study over 12 months. Respir Med. 2022;191:106709.</Citation><ArticleIdList><ArticleId IdType="pmc">PMC8632363</ArticleId><ArticleId IdType="pubmed">34871947</ArticleId></ArticleIdList></Reference><Reference><Citation>M&#xfc;ller S.A., Isaaka L., Mumm R., et al.  Prevalence and risk factors for long COVID and post-COVID-19 condition in Africa: a systematic review. Lancet Glob Health. 2023;11:1713&#x2013;1724. www.thelancet.com/lancetgh Available from:</Citation><ArticleIdList><ArticleId IdType="pubmed">37858583</ArticleId></ArticleIdList></Reference><Reference><Citation>Jassat W., Cohen C., Tempia S., et al. Risk factors for COVID-19-related in-hospital mortality in a high HIV and tuberculosis prevalence setting in South Africa: a cohort study. Lancet HIV. 2021;8(9):e554&#x2013;e567.</Citation><ArticleIdList><ArticleId IdType="pmc">PMC8336996</ArticleId><ArticleId IdType="pubmed">34363789</ArticleId></ArticleIdList></Reference><Reference><Citation>Adams J., Mackenzie M.J., Amegah A.K., et al.  The conundrum of low COVID-19 mortality burden in sub-saharan Africa: myth or reality? Glob Health Sci Pract. 2021;9(3):433&#x2013;443. www.ghspjournal.org Available from:</Citation><ArticleIdList><ArticleId IdType="pmc">PMC8514030</ArticleId><ArticleId IdType="pubmed">34593571</ArticleId></ArticleIdList></Reference><Reference><Citation>National Department of Health South Africa  . Covid-19 Online Resource and News Portal; 2023. National department of health of South Africa.https://sacoronavirus.co.za/covid-19-daily-cases/ [cited 2024 Feb 22] Available from:</Citation></Reference><Reference><Citation>Africa Centre for Disease Control and Prevention, African Union  . Africa CDC COVID-19 Dashboard; 2023. Africa CDC.https://africacdc.org/covid-19/ [cited 2024 Feb 22] Available from:</Citation></Reference><Reference><Citation>Ayles H., Mureithi L., Simwinga M. The state of tuberculosis in South Africa: what does the first national tuberculosis prevalence survey teach us? Lancet. 2022;22:1094&#x2013;1095.</Citation><ArticleIdList><ArticleId IdType="pubmed">35594899</ArticleId></ArticleIdList></Reference><Reference><Citation>Patel R., Kaki M., Potluri V.S., Kahar P., Khanna D. A&#xa0;comprehensive review of SARS-CoV-2 vaccines: pfizer, moderna &amp; johnson &amp; johnson. Hum Vaccin Immunother. 2022;18(1):2002083.</Citation><ArticleIdList><ArticleId IdType="pmc">PMC8862159</ArticleId><ArticleId IdType="pubmed">35130825</ArticleId></ArticleIdList></Reference><Reference><Citation>Ivanova O., Hoffmann V.S., Lange C., Hoelscher M., Rachow A. Post-tuberculosis lung impairment: systematic review and meta-analysis of spirometry data from 14 621 people. Eur Respir Rev. 2023;32:220221.</Citation><ArticleIdList><ArticleId IdType="pmc">PMC10113954</ArticleId><ArticleId IdType="pubmed">37076175</ArticleId></ArticleIdList></Reference><Reference><Citation>Rubio-Rivas M., Mora-Luj&#xe1;n J.M., Formiga F., et al. WHO ordinal scale and inflammation risk categories in COVID-19. Comparative study of the severity scales. J&#xa0;Gen Intern Med. 2022;37(8):1980&#x2013;1987.</Citation><ArticleIdList><ArticleId IdType="pmc">PMC8992782</ArticleId><ArticleId IdType="pubmed">35396659</ArticleId></ArticleIdList></Reference><Reference><Citation>Jones P., Jones P.W., Forde Y. 2009. ST GEORGE&#x2019;S respiratory questionnaire manual.</Citation></Reference><Reference><Citation>Pasipanodya J.G., Miller T.L., Vecino M., et al. Using the St. George respiratory questionnaire to ascertain health quality in persons with treated pulmonary tuberculosis. Chest. 2007;132(5):1591&#x2013;1598.</Citation><ArticleIdList><ArticleId IdType="pubmed">17890471</ArticleId></ArticleIdList></Reference><Reference><Citation>American Thoracic Society Board of Directors  American thoracic society ATS statement: guidelines for the six-minute walk test. Am J Respir Crit Care Med. 2002;166:111&#x2013;117. www.atsjournals.org Available from:</Citation><ArticleIdList><ArticleId IdType="pubmed">12091180</ArticleId></ArticleIdList></Reference><Reference><Citation>Cote C.G., Casanova C., Mar&#xed;n J.M., et al. Validation and comparison of reference equations for the 6-min walk distance test. Eur Respir J. 2008;31(3):571&#x2013;578.</Citation><ArticleIdList><ArticleId IdType="pubmed">17989117</ArticleId></ArticleIdList></Reference><Reference><Citation>Stanojevic S., Kaminsky D.A., Miller M.R., et al. ERS/ATS technical standard on interpretive strategies for routine lung function tests. Eur Respir J. 2022;60(1):2101499.</Citation><ArticleIdList><ArticleId IdType="pubmed">34949706</ArticleId></ArticleIdList></Reference><Reference><Citation>Quanjer P.H., Stanojevic S., Cole T.J., et al. Multi-ethnic reference values for spirometry for the 3-95-yr age range: the global lung function 2012 equations. Eur Respir J. 2012;40(6):1324&#x2013;1343.</Citation><ArticleIdList><ArticleId IdType="pmc">PMC3786581</ArticleId><ArticleId IdType="pubmed">22743675</ArticleId></ArticleIdList></Reference><Reference><Citation>McNutt L.A., Wu C., Xue X., Hafner J.P. Estimating the relative risk in cohort studies and clinical trials of common outcomes. Am J Epidemiol. 2003;157(10):940&#x2013;943.</Citation><ArticleIdList><ArticleId IdType="pubmed">12746247</ArticleId></ArticleIdList></Reference><Reference><Citation>Long Q., Li J., Hu X., Bai Y., Zheng Y., Gao Z. Follow-ups on persistent symptoms and pulmonary function among post-acute COVID-19 patients: a systematic review and meta-analysis. Front Med (Lausanne) 2021;8:702635.</Citation><ArticleIdList><ArticleId IdType="pmc">PMC8448290</ArticleId><ArticleId IdType="pubmed">34540862</ArticleId></ArticleIdList></Reference><Reference><Citation>Sonnweber T., Tymoszuk P., Sahanic S., et al. Investigating phenotypes of pulmonary COVID-19 recovery: a longitudinal observational prospective multicenter trial. Elife. 2022;11:e72500.</Citation><ArticleIdList><ArticleId IdType="pmc">PMC8896831</ArticleId><ArticleId IdType="pubmed">35131031</ArticleId></ArticleIdList></Reference><Reference><Citation>Singh S.J., Baldwin M.M., Daynes E., et al. Respiratory sequelae of COVID-19: pulmonary and extrapulmonary origins, and approaches to clinical care and rehabilitation. Lancet Respir Med. 2023;11:709&#x2013;725.</Citation><ArticleIdList><ArticleId IdType="pmc">PMC10198676</ArticleId><ArticleId IdType="pubmed">37216955</ArticleId></ArticleIdList></Reference><Reference><Citation>Huang Y., Tan C., Wu J., et al. Impact of coronavirus disease 2019 on pulmonary function in early convalescence phase. Respir Res. 2020;21(1):163.</Citation><ArticleIdList><ArticleId IdType="pmc">PMC7323373</ArticleId><ArticleId IdType="pubmed">32600344</ArticleId></ArticleIdList></Reference><Reference><Citation>Wang Y., Dong C., Hu Y., et al. Temporal changes of CT findings in 90 patients with COVID-19 pneumonia: a longitudinal study. Radiology. 2020;296(2):E55&#x2013;E64.</Citation><ArticleIdList><ArticleId IdType="pmc">PMC7233482</ArticleId><ArticleId IdType="pubmed">32191587</ArticleId></ArticleIdList></Reference><Reference><Citation>Ahmed H., Patel K., Greenwood D.C., et al. Long-term clinical outcomes in survivors of severe acute respiratory syndrome (SARS) and Middle East respiratory syndrome (MERS) coronavirus outbreaks after hospitalisation or ICU admission: a systematic review and meta-analysis. J&#xa0;Rehabil Med. 2020;52</Citation><ArticleIdList><ArticleId IdType="pubmed">32449782</ArticleId></ArticleIdList></Reference><Reference><Citation>Katira B.H. Ventilator-induced lung injury: classic and novel concepts. Respir Care. 2019;64(6):629&#x2013;637.</Citation><ArticleIdList><ArticleId IdType="pubmed">31110032</ArticleId></ArticleIdList></Reference><Reference><Citation>Matuschak G.M., Lechner A.J. Acute lung injury and the acute respiratory distress syndrome: pathophysiology and treatment. Mo Med. 2010;107(4):252&#x2013;258.</Citation><ArticleIdList><ArticleId IdType="pmc">PMC6188356</ArticleId><ArticleId IdType="pubmed">20806836</ArticleId></ArticleIdList></Reference><Reference><Citation>Maleche-Obimbo E., Odhiambo M.A., Njeri L., et al. Magnitude and factors associated with post-tuberculosis lung disease in low- and middle-income countries: a systematic review and meta-analysis. PLOS Global Public Health. 2022;2(12)</Citation><ArticleIdList><ArticleId IdType="pmc">PMC10021795</ArticleId><ArticleId IdType="pubmed">36962784</ArticleId></ArticleIdList></Reference><Reference><Citation>Fink D.L., Oladele D., Slack A., et al. A&#xa0;multi-centre observational study of HIV, tuberculosis and risk of chronic lung disease in urban West Africa. AIDS. 2022;36(14):1987&#x2013;1995.</Citation><ArticleIdList><ArticleId IdType="pubmed">35983707</ArticleId></ArticleIdList></Reference><Reference><Citation>Calligaro G.L., Esmail A., Gray D.M. Severe airflow obstruction in vertically acquired HIV infection. Respirol Case Rep. 2014;2(4):135&#x2013;137.</Citation><ArticleIdList><ArticleId IdType="pmc">PMC4263494</ArticleId><ArticleId IdType="pubmed">25530862</ArticleId></ArticleIdList></Reference><Reference><Citation>Hendren N.S., de Lemos J.A., Ayers C., et al. Association of body mass index and age with morbidity and mortality in patients hospitalized with COVID-19:results from the American heart association COVID-19 cardiovascular disease registry. Circulation. 2021;143(2):135&#x2013;144.</Citation><ArticleIdList><ArticleId IdType="pubmed">33200947</ArticleId></ArticleIdList></Reference></ReferenceList></PubmedData></PubmedArticle></PubmedArticleSet>